hyap_auth_manager/__init__.py
hyap_auth_manager/AsymmetricsKeysManager.py
hyap_auth_manager/StandardCypherManager.py
hyap_auth_manager/SymmetricsKeysManager.py
hyap_auth_manager-0.0.4.dist-info/LICENSE
hyap_auth_manager-0.0.4.dist-info/METADATA
hyap_auth_manager-0.0.4.dist-info/WHEEL
hyap_auth_manager-0.0.4.dist-info/RECORD
