Metadata-Version: 2.1
Name: hyap-auth-manager
Version: 0.0.4
Summary: Python package for managing authentication keys based on python.
Home-page: https://github.com/hanifabd/hyap-auth-manager
Keywords: auth,authentication,access,key,web,asymmetrics,symmetrics
Author: Hanif Yuli Abdillah P
Author-email: hanifabd23@gmail.com
Requires-Python: >=3.7
Classifier: License :: OSI Approved :: MIT License
Classifier: Operating System :: OS Independent
Classifier: Programming Language :: Python :: 3
Classifier: Programming Language :: Python :: 3.7
Classifier: Programming Language :: Python :: 3.8
Classifier: Programming Language :: Python :: 3.9
Classifier: Programming Language :: Python :: 3.10
Classifier: Programming Language :: Python :: 3.11
Classifier: Programming Language :: Python :: 3.12
Classifier: Programming Language :: Python :: 3.13
Requires-Dist: cryptography (>=39.0.1,<40.0.0)
Requires-Dist: pyjwt (>=2.5.0,<3.0.0)
Project-URL: Repository, https://github.com/hanifabd/hyap-auth-manager
